{
  "coins": {
    "BTC": {
      "name": "Bitcoin",
      "symbol": "BTC",
      "price": 110620,
      "change_24h": 0.4192514508822326,
      "market_cap": 2203854298912.0703,
      "volume_24h": 31355302875.952698,
      "last_updated": "2025-11-02T14:53:13Z"
    },
    "ETH": {
      "name": "Ethereum",
      "symbol": "ETH",
      "price": 3865.84,
      "change_24h": -0.2740135022072773,
      "market_cap": 466255012341.11115,
      "volume_24h": 13767294506.775642,
      "last_updated": "2025-11-02T14:53:13Z"
    },
    "SOL": {
      "name": "Solana",
      "symbol": "SOL",
      "price": 185.15,
      "change_24h": -0.6106354238002616,
      "market_cap": 102196532633.44618,
      "volume_24h": 2931850827.3187633,
      "last_updated": "2025-11-02T14:53:04Z"
    },
    "HNT": {
      "name": "Helium",
      "symbol": "HNT",
      "price": 2.37,
      "change_24h": -4.756784376138437,
      "market_cap": 440453316.81194764,
      "volume_24h": 9968161.387068026,
      "last_updated": "2025-11-02T14:53:05Z"
    }
  },
  "last_updated": "2025-11-02T14:53:13Z"
}
