{
  "coins": {
    "BTC": {
      "name": "Bitcoin",
      "symbol": "BTC",
      "price": 121772,
      "change_24h": -0.6527552650069977,
      "market_cap": 2426631593078.4473,
      "volume_24h": 56341186760.695274,
      "last_updated": 1760002642
    },
    "ETH": {
      "name": "Ethereum",
      "symbol": "ETH",
      "price": 4350.44,
      "change_24h": -2.8468243778812354,
      "market_cap": 525132121395.2323,
      "volume_24h": 38817823688.77086,
      "last_updated": 1760002642
    },
    "SOL": {
      "name": "Solana",
      "symbol": "SOL",
      "price": 221.6,
      "change_24h": 0.15947789461170478,
      "market_cap": 120901940456.66016,
      "volume_24h": 7818342738.880331,
      "last_updated": 1760002636
    },
    "HNT": {
      "name": "Helium",
      "symbol": "HNT",
      "price": 2.7,
      "change_24h": 10.889051282524427,
      "market_cap": 503956640.38133574,
      "volume_24h": 16399416.760538466,
      "last_updated": 1760002642
    }
  },
  "last_updated": "2025-10-09T09:37:22Z"
}
