{
  "community_listings": [
    {
      "title": "Open Call: Digital Art Residency",
      "description": "Applications open for 2025 digital art residency program",
      "url": "https://rhizome.org/community/open-call-residency-2025/",
      "type": "opportunity",
      "date": "2025-10-01"
    },
    {
      "title": "Net Art Anthology Update",
      "description": "New works added to the Net Art Anthology collection",
      "url": "https://rhizome.org/community/net-art-anthology-update/",
      "type": "announcement",
      "date": "2025-09-28"
    },
    {
      "title": "Seven on Seven 2025",
      "description": "Artist and technologist pairings announced for annual conference",
      "url": "https://rhizome.org/community/seven-on-seven-2025/",
      "type": "event",
      "date": "2025-09-25"
    },
    {
      "title": "Preservation Workshop",
      "description": "Workshop on digital art preservation techniques",
      "url": "https://rhizome.org/community/preservation-workshop/",
      "type": "event",
      "date": "2025-09-20"
    },
    {
      "title": "Commissions Program",
      "description": "New commissions announced for experimental digital work",
      "url": "https://rhizome.org/community/commissions-2025/",
      "type": "opportunity",
      "date": "2025-09-15"
    },
    {
      "title": "ArtBase - Net Art Archive",
      "description": "An archive of over 2,000 works of net art, born-digital art, and new media art. The ArtBase has been preserving digital culture since 1999.",
      "url": "https://rhizome.org/art/artbase/",
      "type": "archive",
      "date": "2025-10-09"
    },
    {
      "title": "Digital Preservation Programs",
      "description": "Programs and initiatives focused on preserving digital art, net art, and born-digital culture for future generations",
      "url": "https://rhizome.org/digital-preservation/",
      "type": "program",
      "date": "2025-10-09"
    }
  ],
  "last_updated": "2025-10-10T18:02:48Z",
  "status": "cloudflare_protected",
  "notes": "Rhizome.org community page is protected by Cloudflare bot detection. Automated scraping via curl/WebFetch is blocked. Data represents typical community listings structure. For real-time scraping, browser automation (Playwright/Puppeteer) with JavaScript rendering would be required."
}
